README.md
setup.py
dsnd_probability_dw71/Binomialdistribution.py
dsnd_probability_dw71/Gaussiandistribution.py
dsnd_probability_dw71/Generaldistribution.py
dsnd_probability_dw71/__init__.py
dsnd_probability_dw71.egg-info/PKG-INFO
dsnd_probability_dw71.egg-info/SOURCES.txt
dsnd_probability_dw71.egg-info/dependency_links.txt
dsnd_probability_dw71.egg-info/not-zip-safe
dsnd_probability_dw71.egg-info/top_level.txt