Metadata-Version: 1.0
Name: dsnd-probability-dw71
Version: 1
Summary: Gaussian and binominal distributions
Home-page: http://www.example.com/~cschultz/bvote/
Author: DataWorks71
Author-email: not@myhome.club
License: UNKNOWN
Platform: UNKNOWN
